README.rst
setup.cfg
setup.py
xl2dict/__init__.py
xl2dict/xlextractor.py
xl2dict.egg-info/PKG-INFO
xl2dict.egg-info/SOURCES.txt
xl2dict.egg-info/dependency_links.txt
xl2dict.egg-info/requires.txt
xl2dict.egg-info/top_level.txt