Metadata-Version: 1.1
Name: xl2dict
Version: 0.1.5
Summary: Spreadsheet to dictionary converter and data explorer
Home-page: https://github.com/gettalent/xl2dict
Author: Ashwin Kondapalli
Author-email: kashwinreddy@gmail.com
License: MIT
Keywords: data driven testing,webdriver,selenium,excel,xls to dict converter,xlsx to dict converter
Platform: UNKNOWN
Classifier: Development Status :: 5 - Production/Stable
Classifier: Intended Audience :: Developers
Classifier: Topic :: Software Development :: Quality Assurance
Classifier: Programming Language :: Python
Classifier: License :: OSI Approved :: MIT License
